LICENSE
MANIFEST.in
README
setup.py
chiki_api/__init__.py
chiki_api/const.py
chiki_api.egg-info/PKG-INFO
chiki_api.egg-info/SOURCES.txt
chiki_api.egg-info/dependency_links.txt
chiki_api.egg-info/not-zip-safe
chiki_api.egg-info/requires.txt
chiki_api.egg-info/top_level.txt