Metadata-Version: 1.0
Name: chiki-api
Version: 0.0.1
Summary: chiki api libs.
Home-page: https://github.com/endsh/chiki-api
Author: Linshao
Author-email: 438985635@qq.com
License: UNKNOWN
Platform: any
